guava3/__init__.py
guava3/conversation.py
guava3/entities.py
guava3/function_library.py
guava3/serializers.py
guava3/utils.py
guava3/implementations/__init__.py
guava3/implementations/images.py
guava3/implementations/notebook.py
guava3/implementations/terminal.py
guava3/implementations/widgets.py
guava3-0.3.dist-info/METADATA
guava3-0.3.dist-info/WHEEL
guava3-0.3.dist-info/top_level.txt
guava3-0.3.dist-info/RECORD
